{"graph":{"metadata":{"threats":["csrf","mitm"],"description":"\nNo *particular* threats to consider at this point.\n\nIt's **extremely** safe."},"edges":[{"metadata":{"operation":"Request /","description":"User navigates with a browser to see some content."},"source":"client","target":"server"},{"metadata":{"operation":"Log","data":["IP Address<sub>OMG</sub>","Timestamp<sub>OMG</sub>","Geolocation<sub>OMG</sub>"],"description":"Logged to a ELK stack."},"source":"server","target":"logs"},{"metadata":{"operation":"Response","data":["User Profile"],"description":"The server responds with some HTML."},"source":"server","target":"client"},{"metadata":{"operation":"Log","data":["Page Navigation"],"description":"The Google Analytics plugin sends navigation\ndata to Google."},"source":"client","target":"analytics"}],"nodes":[{"metadata":{"trust-boundary":"browser","type":"function"},"id":"client","label":"Client"},{"metadata":{"trust-boundary":"aws","type":"function"},"id":"server","label":"Web Server"},{"metadata":{"trust-boundary":"aws","type":"database"},"id":"logs","label":"Logs"},{"metadata":{"type":"io"},"id":"analytics","label":"Google Analytics"}],"label":"Webapp"}}
